graphene_django_extended/__init__.py
graphene_django_extended/connection.py
graphene_django_extended/converter.py
graphene_django_extended/interface.py
graphene_django_extended/mutation.py
graphene_django_extended/_mutations/Pipfile
graphene_django_extended/_mutations/__init__.py
graphene_django_extended/_mutations/delete_mutation.py
graphene_django_extended/_mutations/fields.py
graphene_django_extended/_mutations/global_id_serializer_mutation.py
graphene_django_extended/_mutations/inputs.py
graphene_django_extended/_mutations/model_mutation.py
graphene_django_extended/_mutations/mutations.py
graphene_django_extended/search/__init__.py
graphene_django_extended/search/connection.py
graphene_django_extended/search/field.py
graphene_django_extended/search/node.py
graphene_django_extended/search/types.py
graphene_django_extended/tests/test_interface.py
graphene_django_extended-1.2.3.dist-info/METADATA
graphene_django_extended-1.2.3.dist-info/WHEEL
graphene_django_extended-1.2.3.dist-info/licenses/LICENSE
graphene_django_extended-1.2.3.dist-info/RECORD
