Metadata-Version: 2.3
Name: graphene-django-extended
Version: 1.2.3
Summary: A collection of utility classes to extend the base functionality of graphene_django
Project-URL: Homepage, https://github.com/AztlanEngineering/graphene-django-extended
Project-URL: Issues, https://github.com/AztlanEngineering/graphene-django-extended/issues
License-File: LICENSE
Classifier: License :: OSI Approved :: Mozilla Public License 2.0 (MPL 2.0)
Classifier: Operating System :: OS Independent
Classifier: Programming Language :: Python :: 3
Requires-Python: >=3.9
